slunic/__init__.py
slunic/admin.py
slunic/apps.py
slunic/awards.py
slunic/configs.py
slunic/consts.py
slunic/contexts.py
slunic/feeds.py
slunic/forms.py
slunic/helpers.py
slunic/hooks.py
slunic/managers.py
slunic/middleware.py
slunic/models.py
slunic/paginator.py
slunic/permissions.py
slunic/search_indexes.py
slunic/signals.py
slunic/slunic_hooks.py
slunic/task.py
slunic/urls.py
slunic/utils.py
slunic/version.py
slunic/views.py
slunic/api/__init__.py
slunic/api/apps.py
slunic/api/paginations.py
slunic/api/urls.py
slunic/api/v1/__init__.py
slunic/api/v1/filtersets.py
slunic/api/v1/permissions.py
slunic/api/v1/serializers.py
slunic/api/v1/urls.py
slunic/api/v1/views.py
slunic/management/__init__.py
slunic/management/commands/__init__.py
slunic/management/commands/create_awards.py
slunic/management/commands/init_badges.py
slunic/management/commands/init_bot.py
slunic/management/commands/init_groups.py
slunic/management/commands/rebuild_tree.py
slunic/management/commands/seed_fakes.py
slunic/markdown/__init__.py
slunic/markdown/bleaching.py
slunic/markdown/renderer.py
slunic/markdown/plugins/__init__.py
slunic/markdown/plugins/gist.py
slunic/markdown/plugins/linkify.py
slunic/markdown/plugins/twitter.py
slunic/markdown/plugins/youtube.py
slunic/migrations/0001_initial.py
slunic/migrations/0002_auto_20211025_1348.py
slunic/migrations/0003_auto_20211026_1129.py
slunic/migrations/0004_auto_20211026_1653.py
slunic/migrations/0005_auto_20211026_1704.py
slunic/migrations/0006_profile_role.py
slunic/migrations/0007_page_vote_count.py
slunic/migrations/0008_comment_type.py
slunic/migrations/0009_delete_answer.py
slunic/migrations/0010_comment_is_spam.py
slunic/migrations/0011_auto_20211028_1356.py
slunic/migrations/0012_auto_20211028_2152.py
slunic/migrations/0013_rename_allow_comments_page_comment_enabled.py
slunic/migrations/__init__.py
slunic/static/favicon.ico
slunic/static/easymde/easymde.min.css
slunic/static/easymde/easymde.min.js
slunic/static/easymde/main.css
slunic-0.0.1.dist-info/LICENSE
slunic-0.0.1.dist-info/METADATA
slunic-0.0.1.dist-info/WHEEL
slunic-0.0.1.dist-info/top_level.txt
slunic-0.0.1.dist-info/RECORD
