Metadata-Version: 2.1
Name: slunic
Version: 0.0.1
Summary: Simple QA
Home-page: https://github.com/realnoobs/slunic
Author: Rizki Sasri Dwitama
Author-email: sasri.project@gmail.com
License: MIT
Project-URL: Documentation, https://github.com/realnoobs/slunic
Project-URL: Source, https://github.com/realnoobs/slunic
Project-URL: Tracker, https://github.com/realnoobs/slunic/projects
Platform: UNKNOWN
Classifier: Development Status :: 4 - Beta
Classifier: Environment :: Web Environment
Classifier: Framework :: Django
Classifier: Intended Audience :: Developers
Classifier: License :: OSI Approved :: BSD License
Classifier: Operating System :: OS Independent
Classifier: Programming Language :: Python
Classifier: Programming Language :: Python :: 3
Classifier: Programming Language :: Python :: 3 :: Only
Classifier: Programming Language :: Python :: 3.8
Classifier: Programming Language :: Python :: 3.9
Classifier: Topic :: Internet :: WWW/HTTP
Classifier: Topic :: Internet :: WWW/HTTP :: Dynamic Content
Classifier: Topic :: Internet :: WWW/HTTP :: WSGI
Classifier: Topic :: Software Development :: Libraries :: Python Modules
Classifier: Topic :: Software Development :: Libraries :: Application Frameworks
Requires-Python: >=3.8
License-File: LICENSE
Requires-Dist: Django (==3.2.7)
Requires-Dist: mistune (==2.0.0rc1)
Requires-Dist: requests (>=2.26.0)
Requires-Dist: whoosh (>=2.7.3)
Requires-Dist: bleach (>=4.0.0)
Requires-Dist: Pillow (>=8.3.0)
Requires-Dist: python-dateutil (>=2.8.1)
Requires-Dist: django-mptt (>=0.13.2)
Requires-Dist: django-taggit (>=1.5.1)
Requires-Dist: django-filter (>=2.3.0)
Requires-Dist: django-haystack (>=3.1.0)
Requires-Dist: django-rq (>=2.3.0)
Requires-Dist: django-webpack-loader (>=1.4.0)
Requires-Dist: djangorestframework (>=3.12.1)
